kaya_runner/__init__.py
kaya_runner/app.py
kaya_runner/setup.py
kaya_runner/conf/kaya_runner.conf.json
kaya_runner/kaya_runner/__init__.py
kaya_runner/kaya_runner/app.py
kaya_runner/src/__init__.py
kaya_runner/src/config.py
kaya_runner/tst/__init__.py
kaya_runner/tst/test_config.py
kaya_runner/tst/test_runner.py
src/__init__.py
src/config.py
tst/__init__.py
tst/test_config.py
tst/test_runner.py
kaya_runner-1.10.dist-info/METADATA
kaya_runner-1.10.dist-info/WHEEL
kaya_runner-1.10.dist-info/entry_points.txt
kaya_runner-1.10.dist-info/top_level.txt
kaya_runner-1.10.dist-info/zip-safe
kaya_runner-1.10.dist-info/RECORD
