Metadata-Version: 2.1
Name: kaya-runner
Version: 1.10
Summary: Provides the user a way to create custom strategy modules.
Home-page: https://kaya.wanolabs.com
Download-URL: http://pypi.python.org/pypi/kaya-runner-sdk
Author: Del:Tango
Author-email: alvearesolutions@gmail.com
License: BSD
Project-URL: Documentation, https://kaya.wanolabs.com.readthedocs.io/en/latest
Project-URL: Source, https://github.com/WanoLabs/KayaRunnerSDK
Project-URL: Tracker, https://github.com/WanoLabs/KayaRunnerSDK/issues
Classifier: Intended Audience :: Developers
Classifier: Operating System :: POSIX :: Linux
Classifier: Programming Language :: Python :: 3
Classifier: Programming Language :: Python :: 3.8
Classifier: Programming Language :: Python :: 3.9
Classifier: Programming Language :: Python :: 3.10
Classifier: Programming Language :: Python :: 3.11
Classifier: Topic :: Software Development :: Libraries :: Python Modules
Requires-Dist: Flask
Requires-Dist: gunicorn
Requires-Dist: flake8
Requires-Dist: mypy
Requires-Dist: pylint
